bing_results_scraper/__init__.py
bing_results_scraper/bing_scraper.py
bing_results_scraper-0.5.0.dist-info/LICENSE.txt
bing_results_scraper-0.5.0.dist-info/METADATA
bing_results_scraper-0.5.0.dist-info/WHEEL
bing_results_scraper-0.5.0.dist-info/entry_points.txt
bing_results_scraper-0.5.0.dist-info/top_level.txt
bing_results_scraper-0.5.0.dist-info/RECORD
