Metadata-Version: 2.1
Name: bing-results-scraper
Version: 0.5.0
Summary: Bing Search Scraper - A Python library for retrieving search results from Bing
Author: Renukumar R
Author-email: renu2babu1110@gmail.com
License: MIT License Copyright ©2024 Renukumar R
License-File: LICENSE.txt
Requires-Dist: requests (==2.31.0)
Requires-Dist: beautifulsoup4 (==4.12.2)
Requires-Dist: asyncio (==3.4.3)
Requires-Dist: aiohttp (==3.8.4)
Requires-Dist: nest-asyncio (==1.5.6)
Requires-Dist: tqdm (==4.65.0)
Requires-Dist: uuid (==1.30)
